dockmancli/configuration/__init__.py
dockmancli/configuration/dockman_configuration.py
dockmancli/container/__init__.py
dockmancli/container/dockman_container.py
dockmancli/dockman_docker/__init__.py
dockmancli/dockman_docker/docker_common.py
dockmancli/dockmancli/__init__.py
dockmancli/dockmancli/dockmancli.py
dockmancli/image/__init__.py
dockmancli/image/dockman_image.py
dockmancli/network/__init__.py
dockmancli/network/dockman_network.py
dockmancli/utils/__init__.py
dockmancli/utils/docker_utils.py
dockmancli/utils/dockman_common.py
dockmancli/utils/emjois.py
dockmancli/utils/prompt_utils.py
dockmancli/utils/spinner.py
dockmancli/volume/__init__.py
dockmancli/volume/dockman_volume.py
dockmancli-1.1.0.dist-info/LICENSE
dockmancli-1.1.0.dist-info/METADATA
dockmancli-1.1.0.dist-info/WHEEL
dockmancli-1.1.0.dist-info/entry_points.txt
dockmancli-1.1.0.dist-info/top_level.txt
dockmancli-1.1.0.dist-info/RECORD
