Metadata-Version: 2.1
Name: dockmancli
Version: 1.1.0
Summary: Docker Administrator via CLI
Author: Alberto Rosa
Project-URL: Homepage, https://github.com/MDKPredator/dockmancli
Classifier: Development Status :: 4 - Beta
Classifier: Programming Language :: Python :: 3
Classifier: Operating System :: OS Independent
Classifier: License :: OSI Approved :: GNU General Public License v3 (GPLv3)
Requires-Python: >=3.0
License-File: LICENSE
Requires-Dist: inquirerpy ==0.3.4
Requires-Dist: docker >=7.0.0
Requires-Dist: PyYAML >=6.0.1
Requires-Dist: python-dateutil ==2.8.2
